eda_plugin/__init__.py
eda_plugin/settings.json
eda_plugin/actuators/__init__.py
eda_plugin/actuators/daq.py
eda_plugin/actuators/micro_manager.py
eda_plugin/actuators/pycromanager.py
eda_plugin/analysers/__init__.py
eda_plugin/analysers/image.py
eda_plugin/analysers/keras.py
eda_plugin/examples/__init__.py
eda_plugin/examples/actuators.py
eda_plugin/examples/analysers.py
eda_plugin/examples/interpreters.py
eda_plugin/examples/main.py
eda_plugin/examples/data/__init__.py
eda_plugin/interpreters/__init__.py
eda_plugin/interpreters/frame_rate.py
eda_plugin/utility/ImageInjector.jar
eda_plugin/utility/PythonEventServer.jar
eda_plugin/utility/__init__.py
eda_plugin/utility/data_structures.py
eda_plugin/utility/download_data.py
eda_plugin/utility/eda_gui.py
eda_plugin/utility/event_bus.py
eda_plugin/utility/image_processing.py
eda_plugin/utility/ome_metadata.py
eda_plugin/utility/qt_classes.py
eda_plugin/utility/settings.py
eda_plugin/utility/writers.py
eda_plugin/utility/models/model0_tiling.h5
eda_plugin/utility/models/model1_rescale.h5
tests/__init__.py
tests/utility/__init__.py
tests/utility/conftest.py
tests/utility/test_event_bus.py
tests/utility/test_mm_mocks.py
tests/utility/test_ome_metadata.py
tests/utility/test_writers.py
eda_plugin-0.2.25.dist-info/LICENSE
eda_plugin-0.2.25.dist-info/METADATA
eda_plugin-0.2.25.dist-info/WHEEL
eda_plugin-0.2.25.dist-info/top_level.txt
eda_plugin-0.2.25.dist-info/RECORD
