Metadata-Version: 2.1
Name: eda-plugin
Version: 0.2.25
Summary: Event-driven acquisition
Home-page: https://github.com/wl-stepp/eda_plugin
Author: Willi L. Stepp
Author-email: willi.stepp@epfl.ch
Project-URL: Bug Tracker, https://github.com/wl-stepp/eda_plugin/issues
Classifier: Programming Language :: Python :: 3
Classifier: License :: OSI Approved :: BSD License
Classifier: Operating System :: OS Independent
Requires-Python: >=3.7
License-File: LICENSE
Requires-Dist: pyqt5
Requires-Dist: pycromanager
Requires-Dist: pyqtgraph
Requires-Dist: qimage2ndarray
Requires-Dist: qdarkstyle
Requires-Dist: tifffile
Requires-Dist: zenodo-get
Requires-Dist: docstring-inheritance
Requires-Dist: zarr
Requires-Dist: ome-zarr
Requires-Dist: pymm-eventserver
